{
  "id": "SPL_WEA_06",
  "cardName": "古樹の道標",
  "type": 1,
  "cpCost": 1,
  "aspect": 2,
  "effectKey": "SPELL_DRAW",
  "flavorText": "生命樹の葉が一枚、風に乗って手札に舞い降りる。",
  "rarity": "C",
  "wishTrigger": "-",
  "emotionTag": "Grace",
  "battlePower": 0,
  "wishDamage": 0,
  "wishDamageType": "",
  "keywords": [],
  "baseGaugeDelta": 0,
  "wishDamageDelta": 0,
  "powerDelta": 0,
  "restTargets": 0,
  "removeCondition": "",
  "targetScope": "",
  "drawCount": 1,
  "hpDamagePercent": 0,
  "damageType": "",
  "bounceCount": 0,
  "searchAspect": "",
  "searchType": "",
  "searchCount": 0,
  "destroyCount": 0,
  "ambushType": "",
  "selfPowerDelta": 0,
  "emotionMatch": "",
  "emotionThreshold": 0,
  "lockCount": 0,
  "globalRule": {
    "kind": "",
    "value": 0,
    "condition": ""
  },
  "ownerBonus": {
    "kind": "",
    "value": 0,
    "condition": ""
  },
  "illustrationId": "Incantations/spl_wea_06",
  "title": "大樹が指し示す道",
  "visualDescription": "great tree's guidance, green light pointing the way"
}